README.md
setup.py
avion/__init__.py
avion.egg-info/PKG-INFO
avion.egg-info/SOURCES.txt
avion.egg-info/dependency_links.txt
avion.egg-info/not-zip-safe
avion.egg-info/requires.txt
avion.egg-info/top_level.txt
bluepy/__init__.py
bluepy/blescan.py
bluepy/btle.py
bluepy/get_services.py
bluepy/sensortag.py
csrmesh/__init__.py
csrmesh/crypto.py
csrmesh/gatt.py
csrmesh/lightbulb.py
csrmesh/movecontroller.py