Metadata-Version: 1.1
Name: avion
Version: 0.10
Summary: Python API for controlling Avi-on Bluetooth dimmers
Home-page: http://github.com/mjg59/python-avion
Author: Matthew Garrett
Author-email: mjg59@srcf.ucam.org
License: UNKNOWN
Platform: UNKNOWN
Classifier: Development Status :: 4 - Beta
Classifier: Intended Audience :: Developers
Classifier: License :: OSI Approved :: GNU General Public License v3 or later (GPLv3+)
Classifier: Operating System :: OS Independent
Classifier: Programming Language :: Python
